odoo/addons/account_partner_reconcile/README.rst
odoo/addons/account_partner_reconcile/__init__.py
odoo/addons/account_partner_reconcile/__manifest__.py
odoo/addons/account_partner_reconcile/i18n/account_partner_reconcile.pot
odoo/addons/account_partner_reconcile/i18n/es.po
odoo/addons/account_partner_reconcile/models/__init__.py
odoo/addons/account_partner_reconcile/models/res_partner.py
odoo/addons/account_partner_reconcile/readme/CONFIGURE.rst
odoo/addons/account_partner_reconcile/readme/CONTRIBUTORS.rst
odoo/addons/account_partner_reconcile/readme/DESCRIPTION.rst
odoo/addons/account_partner_reconcile/readme/USAGE.rst
odoo/addons/account_partner_reconcile/static/description/icon.png
odoo/addons/account_partner_reconcile/static/description/index.html
odoo/addons/account_partner_reconcile/tests/__init__.py
odoo/addons/account_partner_reconcile/tests/test_account_partner_reconcile.py
odoo/addons/account_partner_reconcile/views/res_partner_view.xml
odoo13_addon_account_partner_reconcile-13.0.1.0.1.dev4.dist-info/METADATA
odoo13_addon_account_partner_reconcile-13.0.1.0.1.dev4.dist-info/WHEEL
odoo13_addon_account_partner_reconcile-13.0.1.0.1.dev4.dist-info/top_level.txt
odoo13_addon_account_partner_reconcile-13.0.1.0.1.dev4.dist-info/RECORD
